InnoML/__init__.py
InnoML/decision_tree.py
InnoML/knn.py
InnoML/linear_regression.py
InnoML/logistic_regression.py
InnoML/multiple_regression.py
InnoML/random_forest.py
InnoML/utils.py
InnoML-0.1.0.dist-info/METADATA
InnoML-0.1.0.dist-info/WHEEL
InnoML-0.1.0.dist-info/top_level.txt
InnoML-0.1.0.dist-info/RECORD
