Metadata-Version: 2.1
Name: InnoML
Version: 0.1.0
Summary: A collection of machine learning models implemented from scratch
Home-page: https://github.com/SriramR123/InnoML
Author: Sriram
Author-email: sriramachandranram@gmail.com
License: UNKNOWN
Platform: UNKNOWN
Classifier: Programming Language :: Python :: 3
Classifier: License :: OSI Approved :: MIT License
Classifier: Operating System :: OS Independent
Requires-Python: >=3.6
Requires-Dist: numpy
